{
    "v_res": 480,
    "h_res": 640,
    "square_side": 0.1,
    "dist": 100.0,
    "eye": [
        700.0,
        450.0,
        800.0
    ],
    "look_at": [
        0.0,
        0.0,
        0.0
    ],
    "up": [
        0.0,
        0.0,
        1.0
    ],
    "background_color": [
        0,
        0,
        0
    ],
    "ambient_light": [
        19,
        99,
        223
    ],
    "objects": [
        {
            "color": [
                61,
                131,
                97
            ],
            "ka": 0.1,
            "kd": 0.8,
            "ks": 0.5,
            "exp": 8.0,
            "plane": {
                "sample": [
                    -200.0,
                    -200.0,
                    0.0
                ],
                "normal": [
                    0.0,
                    0.0,
                    1.0
                ]
            }
        },
        {
            "color": [
                214,
                205,
                164
            ],
            "ka": 0.1,
            "kd": 0.8,
            "ks": 0.5,
            "exp": 8.0,
            "plane": {
                "sample": [
                    -200.0,
                    -200.0,
                    0.0
                ],
                "normal": [
                    0.0,
                    1.0,
                    0.0
                ]
            }
        },
        {
            "color": [
                214,
                205,
                164
            ],
            "ka": 0.1,
            "kd": 0.8,
            "ks": 0.5,
            "exp": 8.0,
            "plane": {
                "sample": [
                    -200.0,
                    -200.0,
                    0.0
                ],
                "normal": [
                    1.0,
                    0.0,
                    0.0
                ]
            }
        },
        {
            "color": [
                178,
                6,
                0
            ],
            "ka": 0.2,
            "kd": 0.8,
            "ks": 0.9,
            "exp": 10.0,
            "sphere": {
                "center": [
                    200.0,
                    300.0,
                    200.0
                ],
                "radius": 80.0
            }
        },
        {
            "color": [
                49,
                8,
                123
            ],
            "ka": 0.2,
            "kd": 0.8,
            "ks": 0.9,
            "exp": 10.0,
            "sphere": {
                "center": [
                    350.0,
                    0.0,
                    100.0
                ],
                "radius": 50.0
            }
        },
        {
            "color": [
                58,
                176,
                255
            ],
            "ka": 0.2,
            "kd": 0.8,
            "ks": 0.9,
            "exp": 10.0,
            "sphere": {
                "center": [
                    200.0,
                    -50.0,
                    300.0
                ],
                "radius": 100.0
            }
        },
        {
            "color": [
                255,
                95,
                0
            ],
            "ka": 0.1,
            "kd": 0.8,
            "ks": 0.5,
            "exp": 8.0,
            "triangle": [
                [
                    0.0,
                    49.999996,
                    200.0
                ],
                [
                    0.0,
                    -50.000008,
                    200.0
                ],
                [
                    86.602539,
                    -49.999996,
                    49.999992
                ]
            ]
        },
        {
            "color": [
                255,
                95,
                0
            ],
            "ka": 0.1,
            "kd": 0.8,
            "ks": 0.5,
            "exp": 8.0,
            "triangle": [
                [
                    0.0,
                    49.999996,
                    200.0
                ],
                [
                    86.602539,
                    -49.999996,
                    49.999992
                ],
                [
                    86.602539,
                    50.0,
                    49.999992
                ]
            ]
        },
        {
            "color": [
                255,
                95,
                0
            ],
            "ka": 0.1,
            "kd": 0.8,
            "ks": 0.5,
            "exp": 8.0,
            "triangle": [
                [
                    86.602539,
                    50.0,
                    49.999992
                ],
                [
                    86.602539,
                    -49.999996,
                    49.999992
                ],
                [
                    -86.602539,
                    -49.999996,
                    49.999992
                ]
            ]
        },
        {
            "color": [
                255,
                95,
                0
            ],
            "ka": 0.1,
            "kd": 0.8,
            "ks": 0.5,
            "exp": 8.0,
            "triangle": [
                [
                    86.602539,
                    50.0,
                    49.999992
                ],
                [
                    -86.602539,
                    -49.999996,
                    49.999992
                ],
                [
                    -86.602539,
                    50.0,
                    49.999992
                ]
            ]
        },
        {
            "color": [
                255,
                95,
                0
            ],
            "ka": 0.1,
            "kd": 0.8,
            "ks": 0.5,
            "exp": 8.0,
            "triangle": [
                [
                    86.602539,
                    -49.999996,
                    49.999992
                ],
                [
                    0.0,
                    -50.000008,
                    200.0
                ],
                [
                    -86.602539,
                    -49.999996,
                    49.999992
                ]
            ]
        },
        {
            "color": [
                255,
                95,
                0
            ],
            "ka": 0.1,
            "kd": 0.8,
            "ks": 0.5,
            "exp": 8.0,
            "triangle": [
                [
                    -86.602539,
                    50.0,
                    49.999992
                ],
                [
                    -86.602539,
                    -49.999996,
                    49.999992
                ],
                [
                    0.0,
                    -50.000008,
                    200.0
                ]
            ]
        },
        {
            "color": [
                255,
                95,
                0
            ],
            "ka": 0.1,
            "kd": 0.8,
            "ks": 0.5,
            "exp": 8.0,
            "triangle": [
                [
                    -86.602539,
                    50.0,
                    49.999992
                ],
                [
                    0.0,
                    -50.000008,
                    200.0
                ],
                [
                    0.0,
                    49.999996,
                    200.0
                ]
            ]
        },
        {
            "color": [
                255,
                95,
                0
            ],
            "ka": 0.1,
            "kd": 0.8,
            "ks": 0.5,
            "exp": 8.0,
            "triangle": [
                [
                    0.0,
                    49.999996,
                    200.0
                ],
                [
                    86.602539,
                    50.0,
                    49.999992
                ],
                [
                    -86.602539,
                    50.0,
                    49.999992
                ]
            ]
        }
    ],
    "lights": [
        {
            "intensity": [
                50,
                255,
                255
            ],
            "position": [
                700.0,
                800.0,
                600.0
            ]
        },
        {
            "intensity": [
                255,
                50,
                255
            ],
            "position": [
                300.0,
                900.0,
                800.0
            ]
        },
        {
            "intensity": [
                255,
                255,
                50
            ],
            "position": [
                1000.0,
                350.0,
                800.0
            ]
        }
    ]
}